Verilog/Combinational Circuit/comb1.v
module comb1(input D, input X, input A, output L);
    assign L = A | (D & (~X));
endmodule

Verilog/Combinational Circuit/comb1_tb.v
`timescale 1ns/1ps
module comb1_tb();
    reg D, X, A;
    wire L;

    comb1 uut(D, X, A, L);

    initial begin
        $dumpfile("comb1.vcd");
        $dumpvars(0, comb1_tb);

        D = 0; X = 0; A = 0; #20;
        D = 0; X = 0; A = 1; #20;
        D = 0; X = 1; A = 0; #20;
        D = 0; X = 1; A = 1; #20;
        D = 1; X = 0; A = 0; #20;
        D = 1; X = 0; A = 1; #20;
        D = 1; X = 1; A = 0; #20;
        D = 1; X = 1; A = 1; #20;

        $finish;
    end

    initial begin
        $monitor("D=%b X=%b A=%b L=%b", D, X, A, L);
    end

endmodule

Verilog/Combinational Circuit/comb1.vcd
$date
	Fri Jul 19 20:17:15 2024
$end
$version
	Icarus Verilog
$end
$timescale
	1ps
$end
$scope module comb1_tb $end
$var wire 1 ! L $end
$var reg 1 " A $end
$var reg 1 # D $end
$var reg 1 $ X $end
$scope module uut $end
$var wire 1 " A $end
$var wire 1 # D $end
$var wire 1 ! L $end
$var wire 1 $ X $end
$upscope $end
$upscope $end
$enddefinitions $end
$comment Show the parameter values. $end
$dumpall
$end
#0
$dumpvars
0$
0#
0"
0!
$end
#20000
1!
1"
#40000
0!
0"
1$
#60000
1!
1"
#80000
1!
0"
0$
1#
#100000
1"
#120000
0!
0"
1$
#140000
1!
1"
