Verilog/Combinational Circuit/decoder3to8.v
/*
module decoder3to8(input [2:0] A, input E, output [7:0] Y);
    assign Y[7] = E & A[2] & A[1] & A[0];
    assign Y[6] = E & A[2] & A[1] & ~A[0];
    assign Y[5] = E & A[2] & ~A[1] & A[0];
    assign Y[4] = E & A[2] & ~A[1] & ~A[0];
    assign Y[3] = E & ~A[2] & A[1] & A[0];
    assign Y[2] = E & ~A[2] & A[1] & ~A[0];
    assign Y[1] = E & ~A[2] & ~A[1] & A[0];
    assign Y[0] = E & ~A[2] & ~A[1] & ~A[0];
    
endmodule
*/

/*
module decoder3to8(input [2:0] A, input E, output reg [7:0] Y);
    always @(*) begin
        if(E == 1'b0) Y = 8'b00000000;
        else if(A == 3'b000) Y = 8'b00000001;
        else if(A == 3'b001) Y = 8'b00000010;
        else if(A == 3'b010) Y = 8'b00000100;
        else if(A == 3'b011) Y = 8'b00001000;
        else if(A == 3'b100) Y = 8'b00010000;
        else if(A == 3'b101) Y = 8'b00100000;
        else if(A == 3'b110) Y = 8'b01000000;
        else Y = 8'b10000000;
    end
endmodule
*/

module decoder3to8(input [2:0] A, input E, output reg [7:0] Y);
    always @(*) begin
        case ({E, A})
            4'b1000: Y = 8'b00000001;
            4'b1001: Y = 8'b00000010;
            4'b1010: Y = 8'b00000100;
            4'b1011: Y = 8'b00001000;
            4'b1100: Y = 8'b00010000;
            4'b1101: Y = 8'b00100000;
            4'b1110: Y = 8'b01000000;
            4'b1111: Y = 8'b10000000;
            default: Y = 8'b00000000;
        endcase
    end
endmodule

Verilog/Combinational Circuit/decoder3to8_tb.v
`timescale 1ns/1ps
module decoder3to8_tb();
    reg [2:0] A;
    reg E;
    wire [7:0] Y;

    decoder3to8 uut(A, E, Y);
    initial begin
        $dumpfile("decoder3to8.vcd");
        $dumpvars(0, decoder3to8_tb);

        E = 1;
        A = 3'b000; #20;
        A = 3'b001; #20;
        A = 3'b010; #20;
        A = 3'b011; #20;
        A = 3'b100; #20;
        A = 3'b101; #20;
        A = 3'b110; #20;
        A = 3'b111; #20;
        $finish;
    end

    initial begin
        $monitor("A=%b Y=%b", A, Y);
    end
    endmodule

Verilog/Combinational Circuit/decoder3to8.vcd
$date
	Fri Jul 19 23:56:40 2024
$end
$version
	Icarus Verilog
$end
$timescale
	1ps
$end
$scope module decoder3to8_tb $end
$var wire 8 ! Y [7:0] $end
$var reg 3 " A [2:0] $end
$var reg 1 # E $end
$scope module uut $end
$var wire 3 $ A [2:0] $end
$var wire 1 # E $end
$var reg 8 % Y [7:0] $end
$upscope $end
$upscope $end
$enddefinitions $end
$comment Show the parameter values. $end
$dumpall
$end
#0
$dumpvars
b1 %
b0 $
1#
b0 "
b1 !
$end
#20000
b10 !
b10 %
b1 "
b1 $
#40000
b100 !
b100 %
b10 "
b10 $
#60000
b1000 !
b1000 %
b11 "
b11 $
#80000
b10000 !
b10000 %
b100 "
b100 $
#100000
b100000 !
b100000 %
b101 "
b101 $
#120000
b1000000 !
b1000000 %
b110 "
b110 $
#140000
b10000000 !
b10000000 %
b111 "
b111 $
